{
  "indexes": [
    {
      "collectionGroup": "consultations",
      "queryScope": "COLLECTION",
      "fields": [
        {
          "fieldPath": "patientId",
          "order": "ASCENDING"
        },
        {
          "fieldPath": "dateTime",
          "order": "DESCENDING"
        }
      ]
    },
    {
      "collectionGroup": "exams",
      "queryScope": "COLLECTION",
      "fields": [
        {
          "fieldPath": "patientId",
          "order": "ASCENDING"
        },
        {
          "fieldPath": "dateTime",
          "order": "DESCENDING"
        }
      ]
    },
    {
      "collectionGroup": "reminders",
      "queryScope": "COLLECTION",
      "fields": [
        {
          "fieldPath": "patientId",
          "order": "ASCENDING"
        },
        {
          "fieldPath": "dateTime",
          "order": "ASCENDING"
        }
      ]
    }
  ],
  "fieldOverrides": []
}
